phaser/__init__.py
phaser/__main__.py
phaser/builtin_steps.py
phaser/column.py
phaser/constants.py
phaser/context.py
phaser/exceptions.py
phaser/io.py
phaser/phase.py
phaser/pipeline.py
phaser/records.py
phaser/steps.py
phaser/table_diff.py
phaser/cli/__init__.py
phaser/cli/command.py
phaser/cli/main.py
phaser/cli/commands/__init__.py
phaser/cli/commands/debug.py
phaser/cli/commands/describe.py
phaser/cli/commands/diff.py
phaser/cli/commands/run.py
phaser-0.3.dist-info/METADATA
phaser-0.3.dist-info/WHEEL
phaser-0.3.dist-info/licenses/LICENSE
phaser-0.3.dist-info/RECORD
