Metadata-Version: 2.3
Name: phaser
Version: 0.3
Summary: The missing framework and utilities to make complex data pipelines better
Author-email: Lisa Dusseault <lisa@rtfm.com>, Jeff Kolesky <jeff.kolesky@gmail.com>
License-File: LICENSE
Classifier: License :: OSI Approved :: MIT License
Classifier: Programming Language :: Python :: 3
Requires-Python: >=3.11
